[{"artistImageSrc": "https://photos.bandsintown.com/thumb/8552847.jpeg", "properlySizedImageURL": "https://media.bandsintown.com/110x110/8552847.webp", "callToActionRedirectUrl": "https://www.bandsintown.com/e/105957102-manuel-rocheman-at-la-gare-le-gore?came_from=257&utm_medium=web&utm_source=home&utm_campaign=ticket_rsvp", "fallbackImageUrl": "https://assets.prod.bandsintown.com/images/homeIcon/festivalPlaceHolderImage/07.png", "artistName": "Manuel Rocheman", "venueName": "La Gare / Le Gore", "streamingEvent": false, "title": null, "locationText": "Paris, France", "pinIconSrc": "https://assets.prod.bandsintown.com/images/pinIcon.svg", "eventUrl": "https://www.bandsintown.com/e/105957102-manuel-rocheman-at-la-gare-le-gore?came_from=257&utm_medium=web&utm_source=home&utm_campaign=event", "artistUrl": "https://www.bandsintown.com/a/2341680-manuel-rocheman?came_from=257&utm_medium=web&utm_source=home&utm_campaign=event", "watchLiveText": "Watch Live", "isPlus": false, "callToActionText": "Tickets & RSVP", "rsvpCount": "0", "rsvpCountInt": 0, "startsAt": "2024-10-28T21:30:00", "timezone": "Europe/Paris", "displayRule": "datetime", "locale": "en"}]